androidMemoryTool/__init__.py
androidMemoryTool/__main__.py
androidMemoryTool/androidMemoryTool.py
androidMemoryTool/cli_for_tool.py
androidMemoryTool/errors_class.py
androidMemoryTool/CommonAPI/__init__.py
androidMemoryTool/CommonAPI/cross_platform_memory_profiler.py
androidMemoryTool/LinuxAPI/AndroidMemoryTool-Tests.py
androidMemoryTool/LinuxAPI/DataClasses.py
androidMemoryTool/LinuxAPI/ThreadingController.py
androidMemoryTool/LinuxAPI/__init__.py
androidMemoryTool/LinuxAPI/additional_features.py
androidMemoryTool/LinuxAPI/android_memory_tool_linux.py
androidMemoryTool/LinuxAPI/libs_read_writers.py
androidMemoryTool/LinuxAPI/mapping.py
androidMemoryTool/LinuxAPI/search_and_readers.py
androidMemoryTool/LinuxAPI/search_and_writers.py
androidMemoryTool/WindowsAPI/DataClasses.py
androidMemoryTool/WindowsAPI/ThreadingController.py
androidMemoryTool/WindowsAPI/__init__.py
androidMemoryTool/WindowsAPI/android_memory_tool_windows.py
androidMemoryTool/WindowsAPI/complex_api_for_all.py
androidMemoryTool-0.6.3.data/data/LICENSE.md
androidMemoryTool-0.6.3.dist-info/LICENSE.md
androidMemoryTool-0.6.3.dist-info/METADATA
androidMemoryTool-0.6.3.dist-info/WHEEL
androidMemoryTool-0.6.3.dist-info/entry_points.txt
androidMemoryTool-0.6.3.dist-info/top_level.txt
androidMemoryTool-0.6.3.dist-info/RECORD
