Metadata-Version: 2.1
Name: androidMemoryTool
Version: 0.6.3
Summary: Proficiently Managing Runtime RAM Memory for Windows, Android, and Linux Platforms
Home-page: https://github.com/Anonym0usWork1221/android-memorytool
Author: Abdul Moez
Author-email: abdulmoez123456789@gmail.com
License: GPL-3.0 license
Keywords: ps,top,kill,free,lsof,netstat,nice,tty,ionice,uptime,taskmgr,process,df,iotop,iostat,ifconfig,taskset,who,pidof,pmap,smem,pstree,monitoring,ulimit,prlimit,smem,performance,metrics,agent,observability,Memory Profiler,Memory Tool,Memory Leak Detection,Cross-Platform Memory Analysis,Windows Memory Profiling,Linux Memory Monitoring,Android Memory Analyzer,Memory Performance Metrics,Memory Optimization,Software Development Tool,Memory Management,Memory Churn Analysis,Memory Profiling Librar
Classifier: License :: OSI Approved :: GNU General Public License v3 or later (GPLv3+)
Classifier: Operating System :: OS Independent
Classifier: Environment :: Console
Classifier: Intended Audience :: Developers
Classifier: Programming Language :: Python
Classifier: Programming Language :: Python :: 3
Classifier: Operating System :: Microsoft :: Windows :: Windows 10
Classifier: Operating System :: Microsoft :: Windows :: Windows 8
Classifier: Operating System :: Microsoft :: Windows :: Windows 7
Classifier: Topic :: Software Development :: Libraries :: Python Modules
Classifier: Topic :: Software Development :: Quality Assurance
Classifier: Topic :: Utilities
Classifier: Topic :: Software Development :: Embedded Systems
Classifier: Topic :: System :: Operating System
Classifier: Topic :: System :: Systems Administration
Classifier: Topic :: Software Development :: Disassemblers
Classifier: Topic :: Games/Entertainment
Classifier: Topic :: Software Development :: Debuggers
Classifier: Topic :: Software Development :: Libraries :: Python Modules
Classifier: Environment :: Console
Requires-Python: >=3.6
License-File: LICENSE.md
Requires-Dist: psutil
